speaking_character_ai/__init__.py
speaking_character_ai/app.py
Speaking_character_ai-0.1.2.dist-info/METADATA
Speaking_character_ai-0.1.2.dist-info/WHEEL
Speaking_character_ai-0.1.2.dist-info/entry_points.txt
Speaking_character_ai-0.1.2.dist-info/top_level.txt
Speaking_character_ai-0.1.2.dist-info/RECORD
