Metadata-Version: 2.1
Name: Speaking-character-ai
Version: 0.1.2
Summary: A Speaking Character AI is a Python library designed to create virtual characters capable of engaging in interactive conversations. It can synthesize speech, generate text-based dialogue, and animate expressions or gestures in response to user inputs, enhancing the user experience in applications such as games, virtual assistants, and storytelling platforms.
Home-page: https://speakingcharacter.ai/
Author: Speaking Character AI
Author-email: contact@speakingcharacter.ai
Classifier: Development Status :: 3 - Alpha
Classifier: Intended Audience :: Developers
Classifier: License :: OSI Approved :: MIT License
Classifier: Operating System :: OS Independent
Classifier: Programming Language :: Python :: 3
Classifier: Programming Language :: Python :: 3.8
Classifier: Programming Language :: Python :: 3.9
Classifier: Programming Language :: Python :: 3.10
Requires-Python: >=3.8
Requires-Dist: Flask==2.3.3
Requires-Dist: Werkzeug==3.0.1
